classy/__init__.py
classy/cli.py
classy/config.py
classy/core.py
classy/data/classy/classy_data.csv
classy/data/input/classy_data_classified.csv
classy/data/input/classy_data_preprocessed.csv
classy/data/mcfa/mcfa.pkl
classy/data/mixnorm/mixnorm.pkl
classy/data/mixnorm/neighbours.csv
classy/data/nironly_1_classified.csv
classy/features/__init__.py
classy/features/feature.py
classy/features/gui.py
classy/index/__init__.py
classy/index/data.py
classy/index/phase.py
classy/plotting.py
classy/preprocessing.py
classy/sources/__init__.py
classy/sources/akari.py
classy/sources/cds/__init__.py
classy/sources/cds/j_aa_568_l7.py
classy/sources/cds/j_aa_627_a124.py
classy/sources/gaia.py
classy/sources/m4ast.py
classy/sources/manos.py
classy/sources/mithneos.py
classy/sources/pds/__init__.py
classy/sources/pds/ecas.py
classy/sources/pds/fornasier_m_types.py
classy/sources/pds/fornasier_trojans.py
classy/sources/pds/ftcas.py
classy/sources/pds/gartrelleetal.py
classy/sources/pds/hardersenspec.py
classy/sources/pds/hendrix_iue.py
classy/sources/pds/irtf.py
classy/sources/pds/lebofsky_three_micron.py
classy/sources/pds/moskovitz_v_types.py
classy/sources/pds/primass.py
classy/sources/pds/reddy_main_belt.py
classy/sources/pds/reddy_nea.py
classy/sources/pds/reddy_nea_mc.py
classy/sources/pds/reddy_vesta.py
classy/sources/pds/rivkin_three_micron.py
classy/sources/pds/s3os2.py
classy/sources/pds/sawyer.py
classy/sources/pds/scas.py
classy/sources/pds/tfcas.py
classy/sources/pds/vilas.py
classy/sources/pds/willman_iannini.py
classy/sources/private.py
classy/sources/smass.py
classy/taxonomies/__init__.py
classy/taxonomies/bus.py
classy/taxonomies/demeo.py
classy/taxonomies/mahlke/__init__.py
classy/taxonomies/mahlke/decision_tree.py
classy/taxonomies/mahlke/defs.py
classy/taxonomies/mahlke/gmm.py
classy/taxonomies/mahlke/mixnorm.py
classy/taxonomies/tholen.py
classy/utils/__init__.py
classy/utils/download.py
classy/utils/logging.py
classy/utils/progress.py
space_classy-0.8.7.dist-info/LICENSE
space_classy-0.8.7.dist-info/METADATA
space_classy-0.8.7.dist-info/WHEEL
space_classy-0.8.7.dist-info/entry_points.txt
space_classy-0.8.7.dist-info/RECORD
