Metadata-Version: 2.3
Name: space-classy
Version: 0.8.7
Summary: classification tool for minor bodies using reflectance spectra and visual albedos
License: MIT
Author: Max Mahlke
Author-email: max.mahlke@oca.eu
Requires-Python: >=3.8
Classifier: License :: OSI Approved :: MIT License
Classifier: Programming Language :: Python :: 3
Classifier: Programming Language :: Python :: 3.8
Classifier: Programming Language :: Python :: 3.9
Classifier: Programming Language :: Python :: 3.10
Classifier: Programming Language :: Python :: 3.11
Classifier: Programming Language :: Python :: 3.12
Classifier: Programming Language :: Python :: 3.13
Provides-Extra: docs
Provides-Extra: gui
Requires-Dist: aiohttp (>=3.8)
Requires-Dist: click (>=8.1.2)
Requires-Dist: importlib-resources (>=5.10.2)
Requires-Dist: lmfit (>=1.2.0)
Requires-Dist: matplotlib (>=3.7.0)
Requires-Dist: mcfa (>=0.1)
Requires-Dist: numpy (>=1.22.3)
Requires-Dist: pandas (>=1.4.2)
Requires-Dist: rich (>=12.2.0)
Requires-Dist: scikit-learn (>=1.2.1)
Requires-Dist: space-rocks (>=1.9.7)
Project-URL: Documentation, https://classy.readthedocs.io/en/latest/
Project-URL: Homepage, https://github.com/maxmahlke/classy
Project-URL: Repository, https://github.com/maxmahlke/classy.git
